dwm_notebooks/Kmean.ipynb
dwm_notebooks/__init__.py
dwm_notebooks/apriori.ipynb
dwm_notebooks/clustering.ipynb
dwm_notebooks/gemini_chat.py
dwm_notebooks/installer.py
dwm_notebooks/installer_py.py
dwm_notebooks/naive_bayes.ipynb
dwm_notebooks/pagerank.ipynb
dwm_notebooks/text_mining.ipynb
dwm_notebooks/solutionpy/Kmean.py
dwm_notebooks/solutionpy/__init__.py
dwm_notebooks/solutionpy/apriori.py
dwm_notebooks/solutionpy/clustering.py
dwm_notebooks/solutionpy/naive_bayes.py
dwm_notebooks/solutionpy/pagerank.py
dwm_notebooks/solutionpy/text_mining.py
dwm_notebooks-0.4.0.dist-info/METADATA
dwm_notebooks-0.4.0.dist-info/WHEEL
dwm_notebooks-0.4.0.dist-info/entry_points.txt
dwm_notebooks-0.4.0.dist-info/top_level.txt
dwm_notebooks-0.4.0.dist-info/RECORD
