Metadata-Version: 2.4
Name: dwm-notebooks
Version: 0.4.0
Summary: A small package that bundles six ML notebooks and provides a CLI to extract them to a user folder.
Author-email: "(you)" <you@example.com>
Requires-Python: >=3.8
Requires-Dist: importlib-resources; python_version < "3.9"
Requires-Dist: google-generativeai>=0.7.2
